desktop.ini
pybees/__init__.py
pybees/desktop.ini
pybees/setup.py
pybees/bees_algorithm/__init__.py
pybees/bees_algorithm/_base.py
pybees/bees_algorithm/_simple_bees_algorithm.py
pybees/bees_algorithm/desktop.ini
pybees/bees_algorithm/tests/__init__.py
pybees/bees_algorithm/tests/desktop.ini
pybees/bees_algorithm/tests/test_simple_bees.py
pybees/utils/__init__.py
pybees/utils/combinatorial_search.py
pybees/utils/combinatorial_single_obj.py
pybees/utils/continuous_single_obj.py
pybees/utils/desktop.ini
pybees/utils/validation.py
pybees/utils/tests/__init__.py
pybees/utils/tests/desktop.ini
pybees/utils/tests/test_combinatorial_global.py
pybees/utils/tests/test_combinatorial_local.py
pybees/utils/tests/test_combinatorial_single_obj.py
pybees/utils/tests/test_continuous_single_obj.py
pybees/utils/tests/test_validation.py
pybees-0.0.4.dist-info/LICENSE.txt
pybees-0.0.4.dist-info/METADATA
pybees-0.0.4.dist-info/WHEEL
pybees-0.0.4.dist-info/desktop.ini
pybees-0.0.4.dist-info/top_level.txt
pybees-0.0.4.dist-info/RECORD
