Metadata-Version: 2.1
Name: pybees
Version: 0.0.4
Summary: A research toolkit for the Bees algorithm in Python
Home-page: https://github.com/jbmoorhouse/pybees
Author: Joseph Moorhouse
Author-email: moorhouse@live.co.uk
License: UNKNOWN
Platform: UNKNOWN
Classifier: Programming Language :: Python :: 3.6
Classifier: Operating System :: OS Independent
Classifier: Topic :: Scientific/Engineering
Requires-Python: >=3.6
Requires-Dist: numpy (>=1.17.4)
Requires-Dist: scipy (>=1.3.2)
Requires-Dist: plotly (>=4.4.1)
Requires-Dist: tqdm (>=4.40.2)
Requires-Dist: scikit-learn (>=0.22)
Requires-Dist: pandas (>=0.25.3)
